{
  "metadata": {
    "tag": "programming",
    "projectName": "Raycaster",
    "companyName": "",
    "yearString": "2021",
    "yearID": "2021",
    "tasks": "Solo project",
    "description": "A raycaster engine developed in c++.",
    "isFavorite": false,
    "contentFolder": "raycaster",
    "voxelPath": "../data/voxels/Raycaster_voxel.json",
    "gradientBackground": [
      "#FFFFFF",
      "#FFFFFF",
      "#FFFFFF"
    ],
    "gradientGrid": [
      "#ffcf67",
      "#2B2B2B",
      "#d3321d"
    ]
  },
  "content": {
    "title": "Raycaster",
    "tagline": "Crude experimentations in c & c++",
    "header": "header",
    "icons": [
      {
        "name": "C++",
        "image": "cplus"
      }
    ],
    "sections": [
      {
        "type": "category",
        "content": {
          "title": "Concept"
        }
      },
      {
        "type": "spacer",
        "content": {
          "height": 2
        }
      },
      {
        "type": "text-image",
        "content": {
          "paragraph": "I developed a raycaster engine that began as a project in C and later transitioned to C++. The engine supports OpenGL for rendering and includes features like multiple Z heights, which adds verticality to the 2D raycasting technique. It also integrates with Tiled, allowing for easier level design and editing. This project was my first time working with C and C++, making it a valuable learning experience, especially in understanding lower-level programming concepts and graphics rendering.",
          "image": {
            "imageIndex": 1,
            "alt": "project image",
            "position": "left"
          }
        }
      },
      {
        "type": "spacer"
      },
      {
        "type": "gif",
        "content": {
          "legend": "The engine allow for multiple z-height",
          "image": {
            "imageIndex": 2,
            "width": 500,
            "height": 484
          }
        }
      },
      {
        "type": "spacer"
      }
    ]
  }
}